nanopy_scan/__init__.py
nanopy_scan/__main__.py
nanopy_scan/db.py
nanopy_scan/indexer.py
nanopy_scan/main.py
nanopy_scan/networks.py
nanopy_scan/static/app.js
nanopy_scan/static/index.html
nanopy_scan/static/style.css
nanopy_scan-3.0.3.dist-info/METADATA
nanopy_scan-3.0.3.dist-info/WHEEL
nanopy_scan-3.0.3.dist-info/entry_points.txt
nanopy_scan-3.0.3.dist-info/top_level.txt
nanopy_scan-3.0.3.dist-info/RECORD
